{
  "brand": "Airsight",
  "brand_id": "airsight",
  "last_updated": "2025-10-17",
  "source": "ispyconnect.com",
  "entries": [
    {
      "models": [
        "Other",
        "TOTO",
        "X10",
        "x10Airsight",
        "XC36A",
        "xc40a",
        "XX36A",
        "xx38",
        "xx40a",
        "XX41A",
        "xx42a",
        "xx52A",
        "xx60a"
      ],
      "type": "FFMPEG",
      "protocol": "http",
      "port": 0,
      "url": "videostream.asf?user=[USERNAME]&pwd=[PASSWORD]&resolution=64&rate=0"
    },
    {
      "models": [
        "Other",
        "X10",
        "X36A",
        "X38A",
        "xc36a",
        "XC36C",
        "XC38A",
        "XX59"
      ],
      "type": "FFMPEG",
      "protocol": "http",
      "port": 0,
      "url": "videostream.asf?usr=[USERNAME]&pwd=[PASSWORD]"
    },
    {
      "models": [
        "Other"
      ],
      "type": "JPEG",
      "protocol": "http",
      "port": 0,
      "url": "IMAGE.JPG"
    },
    {
      "models": [
        "Other",
        "x10",
        "x10Airsight",
        "X36A",
        "x69",
        "X70A",
        "XC39A",
        "xc49a",
        "XX34A",
        "XX36A",
        "xx39A",
        "xx49a",
        "XX52A",
        "xx59a"
      ],
      "type": "MJPEG",
      "protocol": "http",
      "port": 0,
      "url": "cgi-bin/videostream.cgi?user=[USERNAME]&pwd=[PASSWORD]"
    },
    {
      "models": [
        "Other",
        "x10",
        "x10Airsight",
        "x36a",
        "xc36a",
        "XC38A",
        "xx36",
        "XX36A",
        "xx39a",
        "xx40a",
        "XX41A",
        "xx42a",
        "xx52a"
      ],
      "type": "VLC",
      "protocol": "http",
      "port": 0,
      "url": "videostream.asf?user=[USERNAME]&pwd=[PASSWORD]"
    },
    {
      "models": [
        "Other",
        "Wideeye",
        "x10",
        "X10",
        "x10Airsight",
        "X10AIRSIGHT",
        "X36A",
        "X39A",
        "xc36a",
        "XC36A",
        "xc38",
        "xc38a",
        "XC39A",
        "XC40A",
        "XX34A",
        "xx34c",
        "XX36A",
        "xx40a",
        "XX41A",
        "xx42a",
        "XX42A",
        "xx52a",
        "XX52a",
        "xx59a",
        "XXA36A"
      ],
      "type": "FFMPEG",
      "protocol": "http",
      "port": 0,
      "url": "videostream.asf?user=[USERNAME]&pwd=[PASSWORD]&resolution=[WIDTH]x[HEIGHT]"
    },
    {
      "models": [
        "Other",
        "X10",
        "X39A",
        "XC39A",
        "xx39a",
        "XX49A",
        "xx59",
        "XX59A"
      ],
      "type": "JPEG",
      "protocol": "http",
      "port": 0,
      "url": "cgi-bin/mobile_snapshot.cgi?user=[USERNAME]&pwd=[PASSWORD]"
    },
    {
      "models": [
        "Other",
        "X10",
        "x10Airsight",
        "XC39A",
        "XX34A",
        "xx59A"
      ],
      "type": "JPEG",
      "protocol": "http",
      "port": 0,
      "url": "cgi-bin/video_snapshot.cgi?user=[USERNAME]&pwd=[PASSWORD]"
    },
    {
      "models": [
        "Other",
        "x10Airsight",
        "XC36A",
        "xx40a",
        "XX41A"
      ],
      "type": "FFMPEG",
      "protocol": "http",
      "port": 0,
      "url": "videostream.asf"
    },
    {
      "models": [
        "Other",
        "x10a",
        "X39A",
        "XC36A",
        "XC38A",
        "XX36A",
        "XX41A"
      ],
      "type": "FFMPEG",
      "protocol": "http",
      "port": 0,
      "url": "videostream.asf?user=[USERNAME]&pwd=[PASSWORD]&resolution=32&rate=0"
    },
    {
      "models": [
        "Other",
        "X10AIRSIGHT",
        "X34A"
      ],
      "type": "JPEG",
      "protocol": "http",
      "port": 0,
      "url": "snapshot.cgi"
    },
    {
      "models": [
        "Other",
        "xc36a",
        "xc38a",
        "xx42a"
      ],
      "type": "JPEG",
      "protocol": "http",
      "port": 0,
      "url": "snapshot.jpg?user=[USERNAME]&pwd=[PASSWORD]"
    },
    {
      "models": [
        "Other",
        "X10",
        "X34A",
        "X38A",
        "xc36a",
        "XC38A",
        "XX34A",
        "XX36A",
        "XX40A",
        "xx51a",
        "xx60a"
      ],
      "type": "MJPEG",
      "protocol": "http",
      "port": 0,
      "url": "videostream.cgi?user=[USERNAME]&pwd=[PASSWORD]&resolution=32"
    },
    {
      "models": [
        "Other",
        "X10",
        "X34A",
        "XC38A",
        "XX34A",
        "XX36A",
        "xx40a",
        "xx51A"
      ],
      "type": "MJPEG",
      "protocol": "http",
      "port": 0,
      "url": "videostream.cgi?rate=11"
    },
    {
      "models": [
        "Other",
        "xx52a"
      ],
      "type": "MJPEG",
      "protocol": "http",
      "port": 0,
      "url": "videostream.cgi?user=[USERNAME]&password=[PASSWORD]"
    },
    {
      "models": [
        "Other",
        "XX60A"
      ],
      "type": "MJPEG",
      "protocol": "http",
      "port": 0,
      "url": "videostream.cgi?rate=0&user=[USERNAME]&pwd=[PASSWORD]"
    },
    {
      "models": [
        "Other",
        "xx40a",
        "xx42a"
      ],
      "type": "MJPEG",
      "protocol": "http",
      "port": 0,
      "url": "video.cgi?resolution=VGA"
    },
    {
      "models": [
        "Other"
      ],
      "type": "JPEG",
      "protocol": "http",
      "port": 0,
      "url": "image.jpg"
    },
    {
      "models": [
        "x10",
        "x10a",
        "xx51a"
      ],
      "type": "JPEG",
      "protocol": "http",
      "port": 0,
      "url": "snapshot.cgi?user=[USERNAME]&pwd=[PASSWORD]"
    },
    {
      "models": [
        "X10",
        "x10Airsight",
        "xx51a"
      ],
      "type": "MJPEG",
      "protocol": "http",
      "port": 0,
      "url": "videostream.cgi"
    },
    {
      "models": [
        "X10",
        "xx40a",
        "xx51a"
      ],
      "type": "MJPEG",
      "protocol": "http",
      "port": 0,
      "url": "videostream.cgi?usr=[USERNAME]&pwd=[PASSWORD]"
    },
    {
      "models": [
        "x10a"
      ],
      "type": "FFMPEG",
      "protocol": "http",
      "port": 131,
      "url": "/videostream.asf?usr=[USERNAME]&pwd=[PASSWORD]"
    },
    {
      "models": [
        "X10A",
        "xx52a"
      ],
      "type": "JPEG",
      "protocol": "http",
      "port": 0,
      "url": "snapshot.cgi?camera=[CHANNEL]"
    },
    {
      "models": [
        "X34A",
        "X38A"
      ],
      "type": "JPEG",
      "protocol": "http",
      "port": 0,
      "url": "snapshot.cgi?user=[USERNAME]&pwd=[PASSWORD]&count=0"
    },
    {
      "models": [
        "X34A",
        "xx40a",
        "xx60a"
      ],
      "type": "FFMPEG",
      "protocol": "http",
      "port": 0,
      "url": "videostream.cgi?resolution=8&rate=13"
    },
    {
      "models": [
        "x38a",
        "X39A",
        "X40A",
        "xc36a"
      ],
      "type": "FFMPEG",
      "protocol": "http",
      "port": 0,
      "url": "videostream.asf?user=[USERNAME]&pwd=[PASSWORD]&resolution=[WIDTH]*[HEIGHT]"
    },
    {
      "models": [
        "x40a",
        "xx40a"
      ],
      "type": "MJPEG",
      "protocol": "http",
      "port": 0,
      "url": "VIDEO.CGI"
    },
    {
      "models": [
        "xc36a"
      ],
      "type": "FFMPEG",
      "protocol": "http",
      "port": 80,
      "url": "/videostream.asf?user=[USERNAME]&pwd=[PASSWORD]&resolution=320x240"
    },
    {
      "models": [
        "xc38a",
        "XC39A",
        "XX34A",
        "XX36A"
      ],
      "type": "MJPEG",
      "protocol": "http",
      "port": 0,
      "url": "video.cgi?resolution=[WIDTH]x[HEIGHT]"
    },
    {
      "models": [
        "xx40a",
        "xx51A"
      ],
      "type": "MJPEG",
      "protocol": "http",
      "port": 0,
      "url": "videostream.cgi?user=[USERNAME]&pwd=[PASSWORD]&resolution=32&rate=0"
    },
    {
      "models": [
        "xx51a"
      ],
      "type": "MJPEG",
      "protocol": "http",
      "port": 0,
      "url": "videostream.cgi?user=[USERNAME]&pwd=[PASSWORD]&resolution=32&rate=0"
    },
    {
      "models": [
        "XX59"
      ],
      "type": "VLC",
      "protocol": "http",
      "port": 0,
      "url": "img/video.asf"
    }
  ]
}