{
  "brand": "Aptina",
  "brand_id": "aptina",
  "last_updated": "2025-10-17",
  "source": "ispyconnect.com",
  "entries": [
    {
      "models": [
        "9P006"
      ],
      "type": "FFMPEG",
      "protocol": "rtsp",
      "port": 0,
      "url": "/ucast/11"
    },
    {
      "models": [
        "9P006"
      ],
      "type": "FFMPEG",
      "protocol": "rtsp",
      "port": 0,
      "url": "/mpeg4"
    },
    {
      "models": [
        "ARR0331",
        "MT9M034"
      ],
      "type": "JPEG",
      "protocol": "http",
      "port": 0,
      "url": "snapshot/view[CHANNEL].jpg"
    },
    {
      "models": [
        "ARR0331"
      ],
      "type": "VLC",
      "protocol": "rtsp",
      "port": 0,
      "url": "live/ch00_0"
    },
    {
      "models": [
        "GXV3662HD"
      ],
      "type": "FFMPEG",
      "protocol": "rtsp",
      "port": 10888,
      "url": "/0"
    }
  ]
}