{
  "brand": "Arebi",
  "brand_id": "arebi",
  "last_updated": "2025-10-17",
  "source": "ispyconnect.com",
  "entries": [
    {
      "models": [
        "A10 Plus"
      ],
      "type": "FFMPEG",
      "protocol": "http",
      "port": 0,
      "url": "videostream.asf?user=[USERNAME]&pwd=[PASSWORD]&resolution=[WIDTH]*[HEIGHT]"
    },
    {
      "models": [
        "A10 Plus"
      ],
      "type": "FFMPEG",
      "protocol": "http",
      "port": 0,
      "url": "videostream.asf?user=[USERNAME]&pwd=[PASSWORD]"
    }
  ]
}