{
  "brand": "Cctv Sentry",
  "brand_id": "cctv-sentry",
  "last_updated": "2025-10-17",
  "source": "ispyconnect.com",
  "entries": [
    {
      "models": [
        "180"
      ],
      "type": "JPEG",
      "protocol": "http",
      "port": 0,
      "url": "image.jpg"
    },
    {
      "models": [
        "H264-IPCAM"
      ],
      "type": "JPEG",
      "protocol": "http",
      "port": 0,
      "url": "snap.jpg?JpegCam=[CHANNEL]"
    },
    {
      "models": [
        "Other"
      ],
      "type": "JPEG",
      "protocol": "http",
      "port": 0,
      "url": "cgi-bin/jpg/image.cgi"
    },
    {
      "models": [
        "Other"
      ],
      "type": "VLC",
      "protocol": "rtsp",
      "port": 0,
      "url": "mpeg4"
    }
  ]
}