{
  "brand": "Ctronics",
  "brand_id": "ctronics",
  "last_updated": "2025-10-17",
  "source": "ispyconnect.com",
  "entries": [
    {
      "models": [
        "1024",
        "1080p",
        "224C",
        "245C1080PWS-DP",
        "245C720PWS",
        "246cws720pan",
        "285",
        "295C-B",
        "2K4MPFHD",
        "380",
        "550C",
        "5Mx5",
        "600C",
        "651C720POE",
        "660-4K",
        "700c",
        "700C-2MPB",
        "700C-4MPB",
        "700C-4MPW",
        "720C",
        "720P",
        "760C",
        "AAAA-192503-TEZSJ",
        "C285",
        "c640",
        "c6f0",
        "C6F0SeZ0N0P3L0",
        "C6F0Sg3N0P6L2",
        "C6F0SgZ0N0PaL2",
        "C6F0SgZ0N0PfL2",
        "C6F0SgZ0N0PgL2",
        "C6F0SgZ0N0PnL2",
        "C6F0SgZ3N0P6L2",
        "C6F0SgZ3N0PcL2",
        "C6F0SgZ3N0PdL2",
        "C6F0SoZ0N0PfL2",
        "C6F0SoZ0N0PgL2",
        "C6F0SoZ0N0PnL2",
        "C6F0SoZ3N0P0L2",
        "C6F0SoZ3N0P9L2",
        "C6F0SoZ3N0PfL2",
        "C6F0SpZ3N0PfL2",
        "C6F0SpZ3N0PmL2",
        "C6F0SpZ3N0PnL2",
        "C6F1SgZ3N1P0L2",
        "C9F0SeZ0N0P2L0",
        "camera1",
        "CITPC-275C",
        "CTIC-PTZ270",
        "CTIP-640C",
        "ctipc",
        "CTIPC",
        "CTIPC 270C5MP",
        "CTIPC 600 C",
        "CTIPC-224",
        "CTIPC-224C1080PWS",
        "CTIPC-224C720PWS",
        "CTIPC-225CDS720PA",
        "CTIPC-245C",
        "CTIPC-245C720PWS",
        "CTIPC-260pws",
        "CTIPC-270C5MP",
        "CTIPC-270C5MP-W",
        "CTIPC-275C",
        "CTIPC-275C1080P",
        "ctipc-275c5mp",
        "CTIPC-275C5MP-B",
        "ctipc-285c",
        "CTIPC-285C",
        "CTIPC-285C1080P",
        "CTIPC-285C5MP-B",
        "CTIPC-285C-Z4",
        "CTIPC-285C-Z4B",
        "ctipc-295c",
        "CTIPC-295C-5MP",
        "CTIPC-380C",
        "CTIPC-380C-2MP",
        "ctipc-380c-4mp",
        "CTIPC-380C-BP",
        "CTIPC-500",
        "CTIPC-500C",
        "CTIPC-530C",
        "CTIPC550C",
        "CTIPC-550C-B",
        "CTIPC-570C",
        "CTIPC-590C",
        "CTIPC-620C",
        "CTIPC-640C",
        "CTIPC-650C",
        "CTIPC-680C-P2",
        "CTIPC-690C",
        "CTIPC-690C-2MPWD",
        "CTIPC-690C-2MPWD-EU4G",
        "ctipc-690C-4KS",
        "CTIPC-690C-4MPSD",
        "CTIPC-700C",
        "CTIPC-700C-4MPB",
        "CTIPC-710C-P2",
        "CTIPC-720C",
        "ctipc-750 c",
        "CTIPC-760",
        "CTIPC-760C",
        "CTIPC-770C-B",
        "ctipc-90C1080P",
        "CTIPC-970C",
        "CTIPC-PTZ270",
        "CTIPC-PTZ270-W",
        "CTIPCW 224",
        "CTIPCW-123C1080PW",
        "ctipcw-224c",
        "CTIPO-3C",
        "CTPIC-380C",
        "CT-S20-G",
        "EEEE-138733-DRZRK",
        "LNE4422S-C",
        "Other",
        "PTZ",
        "PTZ270",
        "SSAA-029509-BBBDF",
        "SSAC-530224-DFFFC",
        "SSAK-375766-CABDC"
      ],
      "type": "FFMPEG",
      "protocol": "rtsp",
      "port": 554,
      "url": "/11"
    },
    {
      "models": [
        "1080P",
        "123C720PW",
        "ctipc-123c720",
        "CTIPC-123C720PW",
        "CTIPCW-112C720",
        "CTIPCW-123C1080PW",
        "CTIPCW-123C720PW",
        "CT-S20-G",
        "Other",
        "PWR1"
      ],
      "type": "FFMPEG",
      "protocol": "rtsp",
      "port": 0,
      "url": "/user=[USERNAME]_password=[PASSWORD]_channel=1_stream=0.sdp"
    },
    {
      "models": [
        "1080P",
        "123C720PW",
        "245C1080PWS",
        "245C1080PWS-DP",
        "245C720PWS",
        "660-4k",
        "720P",
        "C6F0SEZ0N0P3L0",
        "C6F0Sg3N0P6L2",
        "C6F0SgZ0N0PfL2",
        "C6F0SgZ3N0PfL2",
        "C6F0SoZ3N0P9L2",
        "C6F0SoZ3N0PcL2",
        "CTIPC-%c",
        "CTIPC-123C720PW",
        "CTIPC-224",
        "CTIPC-224C1080PWS",
        "CTIPC-224C720720PWS",
        "CTIPC-224C720PWS",
        "ctipc-245c",
        "CTIPC-245C1080PWS",
        "CTIPC-245C720PWS",
        "CTIPC-246CWS720PAN",
        "CTIPC-275C1080P",
        "CTIPC-275C5MP-B",
        "CTIPC-285C",
        "CTIPC-285C1080P",
        "CTIPC-290C5MP-B",
        "CTIPC-380C",
        "CTIPC-380C-2MP",
        "CTIPC-520c",
        "CTIPC-780C",
        "CTIPC-C6F0SgZ3N0PdL2",
        "CTIPC-PTZ270",
        "CTIPCW",
        "CTIPCW 224",
        "CTIPCW-245C",
        "CTIPO-350C5MP",
        "Other",
        "PTZ",
        "UNLISTED"
      ],
      "type": "JPEG",
      "protocol": "http",
      "port": 0,
      "url": "tmpfs/auto.jpg"
    },
    {
      "models": [
        "1080P",
        "CTIPCW-IR06B"
      ],
      "type": "JPEG",
      "protocol": "http",
      "port": 0,
      "url": "snapshot.jpg?user=[USERNAME]&pwd=[PASSWORD]&strm=[CHANNEL]"
    },
    {
      "models": [
        "123c720"
      ],
      "type": "FFMPEG",
      "protocol": "rtsp",
      "port": 0,
      "url": "/user=[USERNAME]_password=[PASSWORD]_channel=1_stream=1.sdp"
    },
    {
      "models": [
        "123C720",
        "123C720PW",
        "720P",
        "C6F0Sg3N0P6L2",
        "C6F0SoZ3N0P9L2",
        "CTIPC-123C720PW",
        "ctipc-295c",
        "CTIPC-PTZ270",
        "Other"
      ],
      "type": "JPEG",
      "protocol": "http",
      "port": 0,
      "url": "snap.jpg?JpegCam=[CHANNEL]"
    },
    {
      "models": [
        "246cws720pan"
      ],
      "type": "VLC",
      "protocol": "http",
      "port": 0,
      "url": "iphone/11?[USERNAME]:[PASSWORD]&"
    },
    {
      "models": [
        "295C-B",
        "550",
        "550C",
        "710c",
        "790",
        "c690",
        "C6F0SgZ0N0PnL2",
        "C6F0SoZ0N0PmL2",
        "C6F0SoZ0N0PnL2",
        "C6F0SoZ3N0P9L2",
        "C6F0SoZ3N0PmL2",
        "C6F0SoZ3N0PnL2",
        "camera1",
        "CTIP-640C",
        "CTIPC 760C",
        "CTIPC-285C-Z4",
        "CTIPC-295C-5MP",
        "CTIPC-380C",
        "ctipc-380c-4mp",
        "CTIPC-500C",
        "CTIPC-640C",
        "CTIPC-650C",
        "CTIPC-700",
        "CTIPC-700C-2MPW-Z5",
        "CTIPC-710C",
        "CTIPC-790C",
        "CTIPC-PTZ270-W",
        "Dom",
        "Other"
      ],
      "type": "FFMPEG",
      "protocol": "rtsp",
      "port": 554,
      "url": "/1"
    },
    {
      "models": [
        "295C-B",
        "C6F0SoZ0N0PfL2",
        "CTIPC-380C"
      ],
      "type": "JPEG",
      "protocol": "http",
      "port": 80,
      "url": "/snap.jpg?JpegCam=0"
    },
    {
      "models": [
        "2k4MP",
        "550C",
        "700C",
        "BU-E580",
        "C6F0SgZ3N0PdL2",
        "C6F0SoZ0N0PfL2",
        "C6F0SoZ3N0PcL2",
        "C6F0SoZ3N0PdL2",
        "citpc 700",
        "CITPC-690c",
        "CTIP-640C",
        "CTIPC-2705MP-W-US",
        "CTIPC-275C5MP",
        "ctipc-285c",
        "CTIPC-285C1080P",
        "CTIPC-380C",
        "CTIPC-380C-2MP",
        "CTIPC-380C-BP",
        "CTIPC-510",
        "ctipc-550c",
        "CTIPC-590C",
        "CTIPC-630C",
        "CTIPC-650C",
        "CTIPC-690C-4MPW",
        "CTIPC-720C",
        "CTIPC-770-C",
        "CTIPC-PTZ270-W",
        "CT-S20-G"
      ],
      "type": "FFMPEG",
      "protocol": "rtsp",
      "port": 554,
      "url": "/12"
    },
    {
      "models": [
        "2MP",
        "720p",
        "ctipc-285c",
        "CTIPC-536C1080POE",
        "CTIPC-631C1080POE",
        "CTIPC-631C1090POE",
        "ctipc-631c720poe",
        "CTIPCD-631C720POE",
        "CTIPO-350C5MP",
        "Other"
      ],
      "type": "FFMPEG",
      "protocol": "rtsp",
      "port": 0,
      "url": "/ch01.264"
    },
    {
      "models": [
        "690"
      ],
      "type": "JPEG",
      "protocol": "http",
      "port": 80,
      "url": "/tmp/snap.jpg"
    },
    {
      "models": [
        "C6F1SgZ3N1P0L2",
        "CT-S20-G"
      ],
      "type": "FFMPEG",
      "protocol": "rtsp",
      "port": 444,
      "url": "/"
    },
    {
      "models": [
        "CTIPC-600C"
      ],
      "type": "JPEG",
      "protocol": "http",
      "port": 80,
      "url": "/tmpfs/auto.jpg"
    },
    {
      "models": [
        "CTIPCW-123C1080PW",
        "CTIPCW-IR06B"
      ],
      "type": "JPEG",
      "protocol": "http",
      "port": 0,
      "url": "snapshot.jpg?user=[USERNAME]&pwd=[PASSWORD]"
    }
  ]
}