{
  "brand": "Digisol",
  "brand_id": "digisol",
  "last_updated": "2025-10-17",
  "source": "ispyconnect.com",
  "entries": [
    {
      "models": [
        "3630",
        "dg-sc2600",
        "DG-SC2600",
        "Other"
      ],
      "type": "VLC",
      "protocol": "rtsp",
      "port": 5544,
      "url": "ipcam_h264.sdp"
    },
    {
      "models": [
        "7100P",
        "DG-SC3800P",
        "dg-sc4600pi",
        "dg-sc5800pi"
      ],
      "type": "MJPEG",
      "protocol": "http",
      "port": 0,
      "url": "cgi/mjpg/mjpeg.cgi"
    },
    {
      "models": [
        "dg-sc2600"
      ],
      "type": "JPEG",
      "protocol": "http",
      "port": 0,
      "url": "snapshot.cgi"
    },
    {
      "models": [
        "dg-sc2600",
        "DS SC 3610",
        "Other"
      ],
      "type": "MJPEG",
      "protocol": "http",
      "port": 0,
      "url": "mjpg/video.mjpg"
    },
    {
      "models": [
        "DG-SC2600",
        "DS SC 3630"
      ],
      "type": "JPEG",
      "protocol": "http",
      "port": 0,
      "url": "snapshot.jpg?user=[USERNAME]&pwd=[PASSWORD]"
    },
    {
      "models": [
        "Other"
      ],
      "type": "JPEG",
      "protocol": "http",
      "port": 0,
      "url": "snapshot.jpg?account=[USERNAME]&password=[PASSWORD]"
    },
    {
      "models": [
        "Other",
        "RTSP"
      ],
      "type": "VLC",
      "protocol": "rtsp",
      "port": 0,
      "url": "ipcam.sdp"
    }
  ]
}