{
  "brand": "Onix Usa",
  "brand_id": "onix-usa",
  "last_updated": "2025-10-17",
  "source": "ispyconnect.com",
  "entries": [
    {
      "models": [
        "IP-827/2811",
        "IP-827DN/2811"
      ],
      "type": "VLC",
      "protocol": "rtsp",
      "port": 0,
      "url": "cam0_0"
    },
    {
      "models": [
        "IPD-3MIR"
      ],
      "type": "FFMPEG",
      "protocol": "rtsp",
      "port": 0,
      "url": "/ucast/11"
    },
    {
      "models": [
        "IPD-3MIR"
      ],
      "type": "FFMPEG",
      "protocol": "rtsp",
      "port": 0,
      "url": "/Streaming/Channels/1"
    },
    {
      "models": [
        "IPD-3MIR"
      ],
      "type": "FFMPEG",
      "protocol": "rtsp",
      "port": 0,
      "url": "/11"
    },
    {
      "models": [
        "Other"
      ],
      "type": "JPEG",
      "protocol": "http",
      "port": 0,
      "url": "snapshot.jpg?user=[USERNAME]&pwd=[PASSWORD]"
    }
  ]
}