{
  "brand": "Pipc",
  "brand_id": "pipc",
  "last_updated": "2025-10-17",
  "source": "ispyconnect.com",
  "entries": [
    {
      "models": [
        "480wf"
      ],
      "type": "FFMPEG",
      "protocol": "http",
      "port": 0,
      "url": "videostream.asf"
    },
    {
      "models": [
        "480wf"
      ],
      "type": "MJPEG",
      "protocol": "http",
      "port": 0,
      "url": "videostream.cgi?rate=0"
    },
    {
      "models": [
        "480wf 1"
      ],
      "type": "FFMPEG",
      "protocol": "http",
      "port": 0,
      "url": "videostream.asf?user=[USERNAME]&pwd=[PASSWORD]&resolution=[WIDTH]*[HEIGHT]"
    }
  ]
}