{
  "brand": "Urban Security Group",
  "brand_id": "urban-security-group",
  "last_updated": "2025-10-17",
  "source": "ispyconnect.com",
  "entries": [
    {
      "models": [
        "DK-7043S-GP-AF"
      ],
      "type": "FFMPEG",
      "protocol": "rtsp",
      "port": 0,
      "url": "/user=[USERNAME]_password=[PASSWORD]_channel=1_stream=0.sdp"
    },
    {
      "models": [
        "USGLBH24T200"
      ],
      "type": "JPEG",
      "protocol": "http",
      "port": 0,
      "url": "snap.jpg"
    }
  ]
}